Metadata-Version: 2.1
Name: awslog
Version: 0.1.5
Summary: Show the history and changes between configuration versions of AWS resources
Home-page: https://github.com/jaksi/awslog
Author: Kristóf Jakab
Author-email: jaksi07c8@gmail.com
License: MIT
Keywords: amazon aws config log diff
Platform: UNKNOWN
